[{"date": "19/09/20", "OR": 4725, "HP": 4780, "LP": 4660, "CR": 4710, "DoD": 0, "DoDP": 0, "Rev": 2396200}, {"date": "19/09/19", "OR": 4700, "HP": 4840, "LP": 4690, "CR": 4710, "DoD": 70, "DoDP": 1.5, "Rev": 3478100}, {"date": "19/09/18", "OR": 4740, "HP": 4770, "LP": 4630, "CR": 4640, "DoD": -60, "DoDP": -1.3, "Rev": 2329300}, {"date": "19/09/17", "OR": 4695, "HP": 4795, "LP": 4675, "CR": 4700, "DoD": 20, "DoDP": 0.4, "Rev": 2491300}, {"date": "19/09/13", "OR": 4680, "HP": 4715, "LP": 4565, "CR": 4680, "DoD": 70, "DoDP": 1.5, "Rev": 4133200}, {"date": "19/09/12", "OR": 4565, "HP": 4650, "LP": 4540, "CR": 4610, "DoD": 180, "DoDP": 4.1, "Rev": 3267900}, {"date": "19/09/11", "OR": 4340, "HP": 4435, "LP": 4300, "CR": 4430, "DoD": 20, "DoDP": 0.5, "Rev": 2851500}, {"date": "19/09/10", "OR": 4510, "HP": 4570, "LP": 4410, "CR": 4410, "DoD": -145, "DoDP": -3.2, "Rev": 3122300}, {"date": "19/09/09", "OR": 4615, "HP": 4700, "LP": 4550, "CR": 4555, "DoD": -55, "DoDP": -1.2, "Rev": 3366500}, {"date": "19/09/06", "OR": 4620, "HP": 4675, "LP": 4525, "CR": 4610, "DoD": 5, "DoDP": 0.1, "Rev": 4480700}, {"date": "19/09/05", "OR": 4400, "HP": 4665, "LP": 4375, "CR": 4605, "DoD": 285, "DoDP": 6.6, "Rev": 5540700}, {"date": "19/09/04", "OR": 4250, "HP": 4350, "LP": 4215, "CR": 4320, "DoD": 70, "DoDP": 1.6, "Rev": 3141700}, {"date": "19/09/03", "OR": 4490, "HP": 4500, "LP": 4240, "CR": 4250, "DoD": -190, "DoDP": -4.3, "Rev": 4212800}, {"date": "19/09/02", "OR": 4365, "HP": 4460, "LP": 4355, "CR": 4440, "DoD": 75, "DoDP": 1.7, "Rev": 3032600}, {"date": "19/08/30", "OR": 4225, "HP": 4405, "LP": 4220, "CR": 4365, "DoD": 185, "DoDP": 4.4, "Rev": 3320600}, {"date": "19/08/29", "OR": 4105, "HP": 4195, "LP": 4100, "CR": 4180, "DoD": 75, "DoDP": 1.8, "Rev": 1835400}, {"date": "19/08/28", "OR": 4140, "HP": 4185, "LP": 4085, "CR": 4105, "DoD": -25, "DoDP": -0.6, "Rev": 1890100}, {"date": "19/08/27", "OR": 4195, "HP": 4200, "LP": 4120, "CR": 4130, "DoD": -20, "DoDP": -0.5, "Rev": 1994700}, {"date": "19/08/26", "OR": 4060, "HP": 4170, "LP": 4055, "CR": 4150, "DoD": 0, "DoDP": 0, "Rev": 2428000}, {"date": "19/08/23", "OR": 4120, "HP": 4160, "LP": 4055, "CR": 4150, "DoD": -25, "DoDP": -0.6, "Rev": 2189600}, {"date": "19/08/22", "OR": 4125, "HP": 4220, "LP": 4120, "CR": 4175, "DoD": 65, "DoDP": 1.6, "Rev": 2528100}, {"date": "19/08/21", "OR": 4085, "HP": 4125, "LP": 4070, "CR": 4110, "DoD": 55, "DoDP": 1.4, "Rev": 2335600}, {"date": "19/08/20", "OR": 4000, "HP": 4110, "LP": 3990, "CR": 4055, "DoD": 30, "DoDP": 0.7, "Rev": 3114700}, {"date": "19/08/19", "OR": 4155, "HP": 4165, "LP": 4020, "CR": 4025, "DoD": -75, "DoDP": -1.8, "Rev": 2926100}, {"date": "19/08/16", "OR": 4120, "HP": 4160, "LP": 4080, "CR": 4100, "DoD": -15, "DoDP": -0.4, "Rev": 2786500}, {"date": "19/08/15", "OR": 4150, "HP": 4190, "LP": 4075, "CR": 4115, "DoD": -105, "DoDP": -2.5, "Rev": 5436600}, {"date": "19/08/14", "OR": 4400, "HP": 4440, "LP": 4210, "CR": 4220, "DoD": -80, "DoDP": -1.9, "Rev": 4005300}, {"date": "19/08/13", "OR": 4120, "HP": 4305, "LP": 4110, "CR": 4300, "DoD": 115, "DoDP": 2.7, "Rev": 3259200}, {"date": "19/08/09", "OR": 4270, "HP": 4275, "LP": 4155, "CR": 4185, "DoD": -35, "DoDP": -0.8, "Rev": 2820500}, {"date": "19/08/08", "OR": 4145, "HP": 4280, "LP": 4135, "CR": 4220, "DoD": 125, "DoDP": 3.1, "Rev": 5089900}, {"date": "19/08/07", "OR": 4275, "HP": 4280, "LP": 4055, "CR": 4095, "DoD": -205, "DoDP": -4.8, "Rev": 7055800}, {"date": "19/08/06", "OR": 4130, "HP": 4355, "LP": 4115, "CR": 4300, "DoD": 10, "DoDP": 0.2, "Rev": 5814400}, {"date": "19/08/05", "OR": 4265, "HP": 4300, "LP": 4185, "CR": 4290, "DoD": -10, "DoDP": -0.2, "Rev": 3990200}, {"date": "19/08/02", "OR": 4235, "HP": 4300, "LP": 4210, "CR": 4300, "DoD": -35, "DoDP": -0.8, "Rev": 4544600}, {"date": "19/08/01", "OR": 4195, "HP": 4395, "LP": 4180, "CR": 4335, "DoD": 65, "DoDP": 1.5, "Rev": 3709700}, {"date": "19/07/31", "OR": 4270, "HP": 4335, "LP": 4250, "CR": 4270, "DoD": -35, "DoDP": -0.8, "Rev": 3319700}, {"date": "19/07/30", "OR": 4100, "HP": 4335, "LP": 4095, "CR": 4305, "DoD": 135, "DoDP": 3.2, "Rev": 6026300}, {"date": "19/07/29", "OR": 4080, "HP": 4210, "LP": 4040, "CR": 4170, "DoD": 15, "DoDP": 0.4, "Rev": 4965800}, {"date": "19/07/26", "OR": 4090, "HP": 4205, "LP": 4065, "CR": 4155, "DoD": -5, "DoDP": -0.1, "Rev": 8413100}, {"date": "19/07/25", "OR": 3770, "HP": 4160, "LP": 3750, "CR": 4160, "DoD": 700, "DoDP": 20.2, "Rev": 11620100}, {"date": "19/07/24", "OR": 3415, "HP": 3515, "LP": 3395, "CR": 3460, "DoD": 130, "DoDP": 3.9, "Rev": 4465800}, {"date": "19/07/23", "OR": 3380, "HP": 3395, "LP": 3320, "CR": 3330, "DoD": 30, "DoDP": 0.9, "Rev": 2453200}, {"date": "19/07/22", "OR": 3255, "HP": 3320, "LP": 3250, "CR": 3300, "DoD": 60, "DoDP": 1.9, "Rev": 2729200}, {"date": "19/07/19", "OR": 3130, "HP": 3260, "LP": 3125, "CR": 3240, "DoD": 215, "DoDP": 7.1, "Rev": 3844800}, {"date": "19/07/18", "OR": 3015, "HP": 3070, "LP": 3010, "CR": 3025, "DoD": -35, "DoDP": -1.1, "Rev": 2099600}, {"date": "19/07/17", "OR": 2998, "HP": 3065, "LP": 2956, "CR": 3060, "DoD": 5, "DoDP": 0.2, "Rev": 2155000}, {"date": "19/07/16", "OR": 3085, "HP": 3125, "LP": 3050, "CR": 3055, "DoD": -35, "DoDP": -1.1, "Rev": 2090300}, {"date": "19/07/12", "OR": 3120, "HP": 3125, "LP": 3035, "CR": 3090, "DoD": 10, "DoDP": 0.3, "Rev": 1903400}, {"date": "19/07/11", "OR": 3055, "HP": 3080, "LP": 3045, "CR": 3080, "DoD": 45, "DoDP": 1.5, "Rev": 1382400}, {"date": "19/07/10", "OR": 3055, "HP": 3105, "LP": 3035, "CR": 3035, "DoD": 10, "DoDP": 0.3, "Rev": 2087900}, {"date": "19/07/09", "OR": 3085, "HP": 3100, "LP": 3015, "CR": 3025, "DoD": -60, "DoDP": -1.9, "Rev": 2124000}, {"date": "19/07/08", "OR": 3120, "HP": 3125, "LP": 3070, "CR": 3085, "DoD": -45, "DoDP": -1.4, "Rev": 1805200}, {"date": "19/07/05", "OR": 3090, "HP": 3150, "LP": 3055, "CR": 3130, "DoD": 55, "DoDP": 1.8, "Rev": 1814300}, {"date": "19/07/04", "OR": 3055, "HP": 3095, "LP": 2997, "CR": 3075, "DoD": 50, "DoDP": 1.7, "Rev": 1833200}, {"date": "19/07/03", "OR": 3105, "HP": 3115, "LP": 3005, "CR": 3025, "DoD": -150, "DoDP": -4.7, "Rev": 3128900}, {"date": "19/07/02", "OR": 3115, "HP": 3190, "LP": 3090, "CR": 3175, "DoD": 25, "DoDP": 0.8, "Rev": 2507500}, {"date": "19/07/01", "OR": 3150, "HP": 3165, "LP": 3085, "CR": 3150, "DoD": 185, "DoDP": 6.2, "Rev": 4737000}, {"date": "19/06/28", "OR": 2892, "HP": 2965, "LP": 2885, "CR": 2965, "DoD": 94, "DoDP": 3.3, "Rev": 5340500}, {"date": "19/06/27", "OR": 2833, "HP": 2898, "LP": 2810, "CR": 2871, "DoD": 89, "DoDP": 3.2, "Rev": 3766000}, {"date": "19/06/26", "OR": 2700, "HP": 2836, "LP": 2700, "CR": 2782, "DoD": 95, "DoDP": 3.5, "Rev": 4575600}, {"date": "19/06/25", "OR": 2748, "HP": 2757, "LP": 2674, "CR": 2687, "DoD": -60, "DoDP": -2.2, "Rev": 3108400}, {"date": "19/06/24", "OR": 2699, "HP": 2752, "LP": 2682, "CR": 2747, "DoD": 18, "DoDP": 0.7, "Rev": 1811000}, {"date": "19/06/21", "OR": 2727, "HP": 2765, "LP": 2702, "CR": 2729, "DoD": 2, "DoDP": 0.1, "Rev": 3652800}, {"date": "19/06/20", "OR": 2653, "HP": 2729, "LP": 2597, "CR": 2727, "DoD": 67, "DoDP": 2.5, "Rev": 4008200}, {"date": "19/06/19", "OR": 2643, "HP": 2684, "LP": 2631, "CR": 2660, "DoD": 137, "DoDP": 5.4, "Rev": 4289600}, {"date": "19/06/18", "OR": 2535, "HP": 2568, "LP": 2493, "CR": 2523, "DoD": -6, "DoDP": -0.2, "Rev": 3866800}, {"date": "19/06/17", "OR": 2537, "HP": 2540, "LP": 2471, "CR": 2529, "DoD": -76, "DoDP": -2.9, "Rev": 4268900}, {"date": "19/06/14", "OR": 2570, "HP": 2611, "LP": 2537, "CR": 2605, "DoD": 3, "DoDP": 0.1, "Rev": 5889900}, {"date": "19/06/13", "OR": 2676, "HP": 2679, "LP": 2595, "CR": 2602, "DoD": -137, "DoDP": -5, "Rev": 4469500}, {"date": "19/06/12", "OR": 2883, "HP": 2883, "LP": 2739, "CR": 2739, "DoD": -134, "DoDP": -4.7, "Rev": 4241600}, {"date": "19/06/11", "OR": 2850, "HP": 2881, "LP": 2827, "CR": 2873, "DoD": 27, "DoDP": 0.9, "Rev": 3042700}, {"date": "19/06/10", "OR": 2809, "HP": 2850, "LP": 2796, "CR": 2846, "DoD": 94, "DoDP": 3.4, "Rev": 4323400}, {"date": "19/06/07", "OR": 2711, "HP": 2760, "LP": 2666, "CR": 2752, "DoD": 133, "DoDP": 5.1, "Rev": 4488200}, {"date": "19/06/06", "OR": 2654, "HP": 2670, "LP": 2618, "CR": 2619, "DoD": -40, "DoDP": -1.5, "Rev": 2458900}, {"date": "19/06/05", "OR": 2697, "HP": 2704, "LP": 2630, "CR": 2659, "DoD": 81, "DoDP": 3.1, "Rev": 5163900}, {"date": "19/06/04", "OR": 2517, "HP": 2578, "LP": 2503, "CR": 2578, "DoD": 58, "DoDP": 2.3, "Rev": 3281400}, {"date": "19/06/03", "OR": 2500, "HP": 2527, "LP": 2485, "CR": 2520, "DoD": -31, "DoDP": -1.2, "Rev": 3194500}, {"date": "19/05/31", "OR": 2575, "HP": 2588, "LP": 2537, "CR": 2551, "DoD": -37, "DoDP": -1.4, "Rev": 3506900}, {"date": "19/05/30", "OR": 2570, "HP": 2611, "LP": 2544, "CR": 2588, "DoD": 13, "DoDP": 0.5, "Rev": 3758600}, {"date": "19/05/29", "OR": 2618, "HP": 2624, "LP": 2548, "CR": 2575, "DoD": -107, "DoDP": -4, "Rev": 4616400}, {"date": "19/05/28", "OR": 2655, "HP": 2694, "LP": 2572, "CR": 2682, "DoD": 77, "DoDP": 3, "Rev": 18394900}, {"date": "19/05/27", "OR": 2646, "HP": 2658, "LP": 2593, "CR": 2605, "DoD": -58, "DoDP": -2.2, "Rev": 2566600}, {"date": "19/05/24", "OR": 2620, "HP": 2696, "LP": 2599, "CR": 2663, "DoD": -6, "DoDP": -0.2, "Rev": 4309400}, {"date": "19/05/23", "OR": 2653, "HP": 2685, "LP": 2610, "CR": 2669, "DoD": -70, "DoDP": -2.6, "Rev": 4083600}, {"date": "19/05/22", "OR": 2849, "HP": 2873, "LP": 2726, "CR": 2739, "DoD": -21, "DoDP": -0.8, "Rev": 4221800}, {"date": "19/05/21", "OR": 2684, "HP": 2807, "LP": 2652, "CR": 2760, "DoD": 29, "DoDP": 1.1, "Rev": 5528400}, {"date": "19/05/20", "OR": 2790, "HP": 2828, "LP": 2712, "CR": 2731, "DoD": -74, "DoDP": -2.6, "Rev": 4688800}, {"date": "19/05/17", "OR": 2927, "HP": 2982, "LP": 2803, "CR": 2805, "DoD": -76, "DoDP": -2.6, "Rev": 5158900}, {"date": "19/05/16", "OR": 3060, "HP": 3060, "LP": 2810, "CR": 2881, "DoD": -194, "DoDP": -6.3, "Rev": 6332100}, {"date": "19/05/15", "OR": 2892, "HP": 3075, "LP": 2868, "CR": 3075, "DoD": 179, "DoDP": 6.2, "Rev": 5123400}, {"date": "19/05/14", "OR": 2809, "HP": 2948, "LP": 2760, "CR": 2896, "DoD": 37, "DoDP": 1.3, "Rev": 6299000}, {"date": "19/05/13", "OR": 2939, "HP": 2964, "LP": 2859, "CR": 2859, "DoD": -121, "DoDP": -4.1, "Rev": 3453300}, {"date": "19/05/10", "OR": 3010, "HP": 3080, "LP": 2967, "CR": 2980, "DoD": -20, "DoDP": -0.7, "Rev": 3890700}, {"date": "19/05/09", "OR": 2983, "HP": 3045, "LP": 2975, "CR": 3000, "DoD": -5, "DoDP": -0.2, "Rev": 2889600}, {"date": "19/05/08", "OR": 3000, "HP": 3070, "LP": 2978, "CR": 3005, "DoD": -65, "DoDP": -2.1, "Rev": 3149500}, {"date": "19/05/07", "OR": 3030, "HP": 3090, "LP": 3010, "CR": 3070, "DoD": -70, "DoDP": -2.2, "Rev": 2990500}, {"date": "19/04/26", "OR": 3235, "HP": 3255, "LP": 3075, "CR": 3140, "DoD": -305, "DoDP": -8.9, "Rev": 8444000}, {"date": "19/04/25", "OR": 3350, "HP": 3470, "LP": 3325, "CR": 3445, "DoD": 110, "DoDP": 3.3, "Rev": 4330900}, {"date": "19/04/24", "OR": 3365, "HP": 3385, "LP": 3295, "CR": 3335, "DoD": 30, "DoDP": 0.9, "Rev": 3206500}, {"date": "19/04/23", "OR": 3275, "HP": 3305, "LP": 3205, "CR": 3305, "DoD": 10, "DoDP": 0.3, "Rev": 2457200}, {"date": "19/04/22", "OR": 3335, "HP": 3340, "LP": 3265, "CR": 3295, "DoD": -25, "DoDP": -0.8, "Rev": 2220300}, {"date": "19/04/19", "OR": 3275, "HP": 3340, "LP": 3265, "CR": 3320, "DoD": 110, "DoDP": 3.4, "Rev": 2646500}, {"date": "19/04/18", "OR": 3265, "HP": 3310, "LP": 3185, "CR": 3210, "DoD": -60, "DoDP": -1.8, "Rev": 2933300}, {"date": "19/04/17", "OR": 3160, "HP": 3290, "LP": 3155, "CR": 3270, "DoD": 170, "DoDP": 5.5, "Rev": 4434800}, {"date": "19/04/16", "OR": 3075, "HP": 3120, "LP": 3020, "CR": 3100, "DoD": 10, "DoDP": 0.3, "Rev": 2449900}, {"date": "19/04/15", "OR": 3150, "HP": 3155, "LP": 3070, "CR": 3090, "DoD": -15, "DoDP": -0.5, "Rev": 2777500}, {"date": "19/04/12", "OR": 3070, "HP": 3120, "LP": 3030, "CR": 3105, "DoD": 40, "DoDP": 1.3, "Rev": 3619300}, {"date": "19/04/11", "OR": 3090, "HP": 3095, "LP": 3005, "CR": 3065, "DoD": -30, "DoDP": -1, "Rev": 3150100}, {"date": "19/04/10", "OR": 2995, "HP": 3115, "LP": 2970, "CR": 3095, "DoD": 5, "DoDP": 0.2, "Rev": 3797200}, {"date": "19/04/09", "OR": 2979, "HP": 3100, "LP": 2974, "CR": 3090, "DoD": 116, "DoDP": 3.9, "Rev": 4044300}, {"date": "19/04/08", "OR": 2983, "HP": 3020, "LP": 2928, "CR": 2974, "DoD": 12, "DoDP": 0.4, "Rev": 3888600}, {"date": "19/04/05", "OR": 2844, "HP": 2968, "LP": 2833, "CR": 2962, "DoD": 79, "DoDP": 2.7, "Rev": 4460900}, {"date": "19/04/04", "OR": 2850, "HP": 2934, "LP": 2849, "CR": 2883, "DoD": 58, "DoDP": 2.1, "Rev": 6714800}, {"date": "19/04/03", "OR": 2770, "HP": 2832, "LP": 2757, "CR": 2825, "DoD": 63, "DoDP": 2.3, "Rev": 5461700}, {"date": "19/04/02", "OR": 2722, "HP": 2776, "LP": 2720, "CR": 2762, "DoD": 120, "DoDP": 4.5, "Rev": 5798100}, {"date": "19/04/01", "OR": 2610, "HP": 2658, "LP": 2602, "CR": 2642, "DoD": 69, "DoDP": 2.7, "Rev": 4680800}, {"date": "19/03/29", "OR": 2535, "HP": 2577, "LP": 2511, "CR": 2573, "DoD": 51, "DoDP": 2, "Rev": 3490300}, {"date": "19/03/28", "OR": 2450, "HP": 2532, "LP": 2415, "CR": 2522, "DoD": 18, "DoDP": 0.7, "Rev": 4286700}, {"date": "19/03/27", "OR": 2530, "HP": 2548, "LP": 2471, "CR": 2504, "DoD": -42, "DoDP": -1.6, "Rev": 2890500}, {"date": "19/03/26", "OR": 2506, "HP": 2553, "LP": 2469, "CR": 2546, "DoD": 48, "DoDP": 1.9, "Rev": 2969500}, {"date": "19/03/25", "OR": 2500, "HP": 2525, "LP": 2486, "CR": 2498, "DoD": -80, "DoDP": -3.1, "Rev": 4074500}, {"date": "19/03/22", "OR": 2528, "HP": 2588, "LP": 2520, "CR": 2578, "DoD": 150, "DoDP": 6.2, "Rev": 5971800}, {"date": "19/03/20", "OR": 2437, "HP": 2444, "LP": 2424, "CR": 2428, "DoD": 0, "DoDP": 0, "Rev": 2502600}, {"date": "19/03/19", "OR": 2423, "HP": 2449, "LP": 2416, "CR": 2428, "DoD": -12, "DoDP": -0.5, "Rev": 4699100}, {"date": "19/03/18", "OR": 2433, "HP": 2449, "LP": 2411, "CR": 2440, "DoD": 51, "DoDP": 2.1, "Rev": 4515200}, {"date": "19/03/15", "OR": 2409, "HP": 2416, "LP": 2375, "CR": 2389, "DoD": 11, "DoDP": 0.5, "Rev": 4492200}, {"date": "19/03/14", "OR": 2459, "HP": 2467, "LP": 2372, "CR": 2378, "DoD": -71, "DoDP": -2.9, "Rev": 4708000}, {"date": "19/03/13", "OR": 2510, "HP": 2519, "LP": 2437, "CR": 2449, "DoD": -57, "DoDP": -2.3, "Rev": 3990000}, {"date": "19/03/12", "OR": 2593, "HP": 2600, "LP": 2505, "CR": 2506, "DoD": 13, "DoDP": 0.5, "Rev": 3802900}, {"date": "19/03/11", "OR": 2529, "HP": 2535, "LP": 2458, "CR": 2493, "DoD": -38, "DoDP": -1.5, "Rev": 4567800}, {"date": "19/03/08", "OR": 2638, "HP": 2642, "LP": 2527, "CR": 2531, "DoD": -152, "DoDP": -5.7, "Rev": 7073700}, {"date": "19/03/07", "OR": 2705, "HP": 2706, "LP": 2644, "CR": 2683, "DoD": -68, "DoDP": -2.5, "Rev": 4429300}, {"date": "19/03/06", "OR": 2732, "HP": 2777, "LP": 2728, "CR": 2751, "DoD": -5, "DoDP": -0.2, "Rev": 2821000}, {"date": "19/03/05", "OR": 2765, "HP": 2808, "LP": 2730, "CR": 2756, "DoD": -77, "DoDP": -2.7, "Rev": 4607500}, {"date": "19/03/04", "OR": 2751, "HP": 2875, "LP": 2751, "CR": 2833, "DoD": 96, "DoDP": 3.5, "Rev": 5378400}, {"date": "19/03/01", "OR": 2670, "HP": 2751, "LP": 2669, "CR": 2737, "DoD": 108, "DoDP": 4.1, "Rev": 5163500}, {"date": "19/02/28", "OR": 2593, "HP": 2649, "LP": 2566, "CR": 2629, "DoD": 36, "DoDP": 1.4, "Rev": 3923300}, {"date": "19/02/27", "OR": 2610, "HP": 2648, "LP": 2591, "CR": 2593, "DoD": -14, "DoDP": -0.5, "Rev": 2334900}, {"date": "19/02/26", "OR": 2617, "HP": 2632, "LP": 2580, "CR": 2607, "DoD": -1, "DoDP": 0, "Rev": 2736400}, {"date": "19/02/25", "OR": 2651, "HP": 2669, "LP": 2607, "CR": 2608, "DoD": 1, "DoDP": 0, "Rev": 2490500}, {"date": "19/02/22", "OR": 2595, "HP": 2630, "LP": 2577, "CR": 2607, "DoD": -38, "DoDP": -1.4, "Rev": 4876200}, {"date": "19/02/21", "OR": 2699, "HP": 2705, "LP": 2644, "CR": 2645, "DoD": -59, "DoDP": -2.2, "Rev": 4647800}, {"date": "19/02/20", "OR": 2713, "HP": 2734, "LP": 2687, "CR": 2704, "DoD": 2, "DoDP": 0.1, "Rev": 2641500}, {"date": "19/02/19", "OR": 2686, "HP": 2729, "LP": 2680, "CR": 2702, "DoD": -9, "DoDP": -0.3, "Rev": 2234300}, {"date": "19/02/18", "OR": 2742, "HP": 2755, "LP": 2696, "CR": 2711, "DoD": 22, "DoDP": 0.8, "Rev": 2465800}, {"date": "19/02/15", "OR": 2743, "HP": 2749, "LP": 2666, "CR": 2689, "DoD": -13, "DoDP": -0.5, "Rev": 4906900}, {"date": "19/02/14", "OR": 2663, "HP": 2724, "LP": 2662, "CR": 2702, "DoD": 42, "DoDP": 1.6, "Rev": 4529100}, {"date": "19/02/13", "OR": 2600, "HP": 2694, "LP": 2594, "CR": 2660, "DoD": 109, "DoDP": 4.3, "Rev": 7062300}, {"date": "19/02/12", "OR": 2500, "HP": 2566, "LP": 2478, "CR": 2551, "DoD": 121, "DoDP": 5, "Rev": 3999500}, {"date": "19/02/08", "OR": 2450, "HP": 2483, "LP": 2413, "CR": 2430, "DoD": -96, "DoDP": -3.8, "Rev": 5534200}, {"date": "19/02/07", "OR": 2581, "HP": 2625, "LP": 2516, "CR": 2526, "DoD": -46, "DoDP": -1.8, "Rev": 4292400}, {"date": "19/02/06", "OR": 2571, "HP": 2609, "LP": 2550, "CR": 2572, "DoD": 24, "DoDP": 0.9, "Rev": 3692100}, {"date": "19/02/05", "OR": 2516, "HP": 2559, "LP": 2512, "CR": 2548, "DoD": 43, "DoDP": 1.7, "Rev": 3555700}, {"date": "19/02/04", "OR": 2461, "HP": 2518, "LP": 2453, "CR": 2505, "DoD": 26, "DoDP": 1, "Rev": 3544500}, {"date": "19/02/01", "OR": 2464, "HP": 2535, "LP": 2463, "CR": 2479, "DoD": 6, "DoDP": 0.2, "Rev": 5645600}, {"date": "19/01/31", "OR": 2405, "HP": 2487, "LP": 2353, "CR": 2473, "DoD": 181, "DoDP": 7.9, "Rev": 11507200}, {"date": "19/01/30", "OR": 2317, "HP": 2334, "LP": 2255, "CR": 2292, "DoD": -6, "DoDP": -0.3, "Rev": 5875500}, {"date": "19/01/29", "OR": 2309, "HP": 2315, "LP": 2222, "CR": 2298, "DoD": -111, "DoDP": -4.6, "Rev": 6907300}, {"date": "19/01/28", "OR": 2392, "HP": 2435, "LP": 2384, "CR": 2409, "DoD": 2, "DoDP": 0.1, "Rev": 4310500}, {"date": "19/01/25", "OR": 2345, "HP": 2424, "LP": 2344, "CR": 2407, "DoD": 112, "DoDP": 4.9, "Rev": 6218800}, {"date": "19/01/24", "OR": 2177, "HP": 2302, "LP": 2169, "CR": 2295, "DoD": 133, "DoDP": 6.2, "Rev": 6758000}, {"date": "19/01/23", "OR": 2160, "HP": 2204, "LP": 2122, "CR": 2162, "DoD": -21, "DoDP": -1, "Rev": 3516600}, {"date": "19/01/22", "OR": 2193, "HP": 2245, "LP": 2179, "CR": 2183, "DoD": -24, "DoDP": -1.1, "Rev": 3146300}, {"date": "19/01/21", "OR": 2250, "HP": 2270, "LP": 2174, "CR": 2207, "DoD": -43, "DoDP": -1.9, "Rev": 4975400}, {"date": "19/01/18", "OR": 2244, "HP": 2261, "LP": 2195, "CR": 2250, "DoD": 41, "DoDP": 1.9, "Rev": 4771900}, {"date": "19/01/17", "OR": 2288, "HP": 2292, "LP": 2164, "CR": 2209, "DoD": -77, "DoDP": -3.4, "Rev": 5383400}, {"date": "19/01/16", "OR": 2399, "HP": 2413, "LP": 2282, "CR": 2286, "DoD": -93, "DoDP": -3.9, "Rev": 4523300}, {"date": "19/01/15", "OR": 2292, "HP": 2387, "LP": 2287, "CR": 2379, "DoD": 62, "DoDP": 2.7, "Rev": 3772200}, {"date": "19/01/11", "OR": 2264, "HP": 2335, "LP": 2247, "CR": 2317, "DoD": 83, "DoDP": 3.7, "Rev": 5767900}, {"date": "19/01/10", "OR": 2200, "HP": 2245, "LP": 2180, "CR": 2234, "DoD": 50, "DoDP": 2.3, "Rev": 4680400}, {"date": "19/01/09", "OR": 2218, "HP": 2220, "LP": 2123, "CR": 2184, "DoD": -55, "DoDP": -2.5, "Rev": 5524300}, {"date": "19/01/08", "OR": 2254, "HP": 2264, "LP": 2185, "CR": 2239, "DoD": -11, "DoDP": -0.5, "Rev": 4976400}, {"date": "19/01/07", "OR": 2226, "HP": 2287, "LP": 2222, "CR": 2250, "DoD": 98, "DoDP": 4.6, "Rev": 3185500}, {"date": "19/01/04", "OR": 2145, "HP": 2152, "LP": 1999, "CR": 2152, "DoD": -92, "DoDP": -4.1, "Rev": 7325600}, {"date": "18/12/28", "OR": 2181, "HP": 2268, "LP": 2181, "CR": 2244, "DoD": 43, "DoDP": 2, "Rev": 3933600}, {"date": "18/12/27", "OR": 2199, "HP": 2223, "LP": 2155, "CR": 2201, "DoD": 110, "DoDP": 5.3, "Rev": 4495700}, {"date": "18/12/26", "OR": 2123, "HP": 2147, "LP": 2039, "CR": 2091, "DoD": 0, "DoDP": 0, "Rev": 4120800}, {"date": "18/12/25", "OR": 2068, "HP": 2139, "LP": 2068, "CR": 2091, "DoD": -62, "DoDP": -2.9, "Rev": 5501200}, {"date": "18/12/21", "OR": 2077, "HP": 2154, "LP": 2076, "CR": 2153, "DoD": 41, "DoDP": 1.9, "Rev": 4657700}, {"date": "18/12/20", "OR": 2120, "HP": 2166, "LP": 2072, "CR": 2112, "DoD": -86, "DoDP": -3.9, "Rev": 5866000}, {"date": "18/12/19", "OR": 2138, "HP": 2212, "LP": 2090, "CR": 2198, "DoD": 59, "DoDP": 2.8, "Rev": 5487400}, {"date": "18/12/18", "OR": 2075, "HP": 2161, "LP": 2069, "CR": 2139, "DoD": 20, "DoDP": 0.9, "Rev": 5083600}, {"date": "18/12/17", "OR": 2084, "HP": 2156, "LP": 2083, "CR": 2119, "DoD": 43, "DoDP": 2.1, "Rev": 3118900}, {"date": "18/12/14", "OR": 2104, "HP": 2129, "LP": 2037, "CR": 2076, "DoD": -57, "DoDP": -2.7, "Rev": 6034800}, {"date": "18/12/13", "OR": 2151, "HP": 2159, "LP": 2109, "CR": 2133, "DoD": 24, "DoDP": 1.1, "Rev": 3541500}, {"date": "18/12/12", "OR": 2097, "HP": 2147, "LP": 2062, "CR": 2109, "DoD": 52, "DoDP": 2.5, "Rev": 5489200}, {"date": "18/12/11", "OR": 2099, "HP": 2139, "LP": 2031, "CR": 2057, "DoD": -14, "DoDP": -0.7, "Rev": 5288400}, {"date": "18/12/10", "OR": 2065, "HP": 2111, "LP": 2053, "CR": 2071, "DoD": -68, "DoDP": -3.2, "Rev": 4870800}, {"date": "18/12/07", "OR": 2218, "HP": 2222, "LP": 2120, "CR": 2139, "DoD": -39, "DoDP": -1.8, "Rev": 4864000}, {"date": "18/12/06", "OR": 2250, "HP": 2256, "LP": 2132, "CR": 2178, "DoD": -122, "DoDP": -5.3, "Rev": 6890500}, {"date": "18/12/05", "OR": 2335, "HP": 2360, "LP": 2282, "CR": 2300, "DoD": -111, "DoDP": -4.6, "Rev": 6041700}, {"date": "18/12/04", "OR": 2498, "HP": 2517, "LP": 2400, "CR": 2411, "DoD": -64, "DoDP": -2.6, "Rev": 4751800}, {"date": "18/12/03", "OR": 2496, "HP": 2519, "LP": 2473, "CR": 2475, "DoD": 39, "DoDP": 1.6, "Rev": 3146500}, {"date": "18/11/30", "OR": 2415, "HP": 2455, "LP": 2394, "CR": 2436, "DoD": -3, "DoDP": -0.1, "Rev": 3278000}, {"date": "18/11/29", "OR": 2448, "HP": 2482, "LP": 2433, "CR": 2439, "DoD": 48, "DoDP": 2, "Rev": 3694700}, {"date": "18/11/28", "OR": 2335, "HP": 2396, "LP": 2317, "CR": 2391, "DoD": 48, "DoDP": 2, "Rev": 3546000}, {"date": "18/11/27", "OR": 2317, "HP": 2359, "LP": 2288, "CR": 2343, "DoD": 48, "DoDP": 2.1, "Rev": 3834400}, {"date": "18/11/26", "OR": 2262, "HP": 2317, "LP": 2245, "CR": 2295, "DoD": 50, "DoDP": 2.2, "Rev": 3692100}, {"date": "18/11/22", "OR": 2269, "HP": 2286, "LP": 2220, "CR": 2245, "DoD": -3, "DoDP": -0.1, "Rev": 3668300}, {"date": "18/11/21", "OR": 2128, "HP": 2262, "LP": 2116, "CR": 2248, "DoD": 96, "DoDP": 4.5, "Rev": 5749100}, {"date": "18/11/20", "OR": 2155, "HP": 2204, "LP": 2144, "CR": 2152, "DoD": -60, "DoDP": -2.7, "Rev": 3600500}, {"date": "18/11/19", "OR": 2181, "HP": 2264, "LP": 2181, "CR": 2212, "DoD": 48, "DoDP": 2.2, "Rev": 3997600}, {"date": "18/11/16", "OR": 2316, "HP": 2316, "LP": 2154, "CR": 2164, "DoD": -177, "DoDP": -7.6, "Rev": 6265800}, {"date": "18/11/15", "OR": 2270, "HP": 2364, "LP": 2251, "CR": 2341, "DoD": 25, "DoDP": 1.1, "Rev": 3251300}, {"date": "18/11/14", "OR": 2299, "HP": 2345, "LP": 2272, "CR": 2316, "DoD": 67, "DoDP": 3, "Rev": 4062900}, {"date": "18/11/13", "OR": 2200, "HP": 2259, "LP": 2176, "CR": 2249, "DoD": -75, "DoDP": -3.2, "Rev": 6536300}, {"date": "18/11/12", "OR": 2378, "HP": 2421, "LP": 2303, "CR": 2324, "DoD": -134, "DoDP": -5.5, "Rev": 8174600}, {"date": "18/11/09", "OR": 2517, "HP": 2531, "LP": 2452, "CR": 2458, "DoD": -59, "DoDP": -2.3, "Rev": 3790000}, {"date": "18/11/08", "OR": 2545, "HP": 2557, "LP": 2502, "CR": 2517, "DoD": 43, "DoDP": 1.7, "Rev": 3975900}, {"date": "18/11/07", "OR": 2428, "HP": 2524, "LP": 2421, "CR": 2474, "DoD": 24, "DoDP": 1, "Rev": 4473900}, {"date": "18/11/06", "OR": 2417, "HP": 2524, "LP": 2416, "CR": 2450, "DoD": 40, "DoDP": 1.7, "Rev": 6850600}, {"date": "18/11/05", "OR": 2370, "HP": 2471, "LP": 2361, "CR": 2410, "DoD": 7, "DoDP": 0.3, "Rev": 6108000}, {"date": "18/11/02", "OR": 2247, "HP": 2440, "LP": 2235, "CR": 2403, "DoD": 178, "DoDP": 8, "Rev": 12085100}, {"date": "18/11/01", "OR": 2151, "HP": 2273, "LP": 2105, "CR": 2225, "DoD": 144, "DoDP": 6.9, "Rev": 11530800}, {"date": "18/10/31", "OR": 2203, "HP": 2203, "LP": 1974, "CR": 2081, "DoD": 238, "DoDP": 12.9, "Rev": 20004200}, {"date": "18/10/30", "OR": 1804, "HP": 1897, "LP": 1788, "CR": 1843, "DoD": 40, "DoDP": 2.2, "Rev": 7788200}, {"date": "18/10/29", "OR": 1863, "HP": 1893, "LP": 1800, "CR": 1803, "DoD": -44, "DoDP": -2.4, "Rev": 4685300}, {"date": "18/10/26", "OR": 1920, "HP": 1941, "LP": 1807, "CR": 1847, "DoD": -44, "DoDP": -2.3, "Rev": 4821600}, {"date": "18/10/25", "OR": 1956, "HP": 1960, "LP": 1886, "CR": 1891, "DoD": -205, "DoDP": -9.8, "Rev": 7107700}, {"date": "18/10/24", "OR": 2159, "HP": 2169, "LP": 2068, "CR": 2096, "DoD": -18, "DoDP": -0.9, "Rev": 4351700}, {"date": "18/10/23", "OR": 2173, "HP": 2185, "LP": 2102, "CR": 2114, "DoD": -84, "DoDP": -3.8, "Rev": 3391800}, {"date": "18/10/22", "OR": 2149, "HP": 2202, "LP": 2133, "CR": 2198, "DoD": 21, "DoDP": 1, "Rev": 2071200}, {"date": "18/10/19", "OR": 2150, "HP": 2181, "LP": 2121, "CR": 2177, "DoD": -39, "DoDP": -1.8, "Rev": 3038400}, {"date": "18/10/18", "OR": 2236, "HP": 2245, "LP": 2208, "CR": 2216, "DoD": -14, "DoDP": -0.6, "Rev": 2379600}, {"date": "18/10/17", "OR": 2215, "HP": 2248, "LP": 2207, "CR": 2230, "DoD": 76, "DoDP": 3.5, "Rev": 3756300}, {"date": "18/10/16", "OR": 2171, "HP": 2177, "LP": 2111, "CR": 2154, "DoD": 0, "DoDP": 0, "Rev": 3400500}, {"date": "18/10/15", "OR": 2160, "HP": 2178, "LP": 2127, "CR": 2154, "DoD": -19, "DoDP": -0.9, "Rev": 2887100}, {"date": "18/10/12", "OR": 2051, "HP": 2180, "LP": 2051, "CR": 2173, "DoD": 91, "DoDP": 4.4, "Rev": 4547700}, {"date": "18/10/11", "OR": 2047, "HP": 2106, "LP": 2004, "CR": 2082, "DoD": -98, "DoDP": -4.5, "Rev": 4969400}, {"date": "18/10/10", "OR": 2200, "HP": 2227, "LP": 2145, "CR": 2180, "DoD": 17, "DoDP": 0.8, "Rev": 2799900}, {"date": "18/10/09", "OR": 2160, "HP": 2184, "LP": 2119, "CR": 2163, "DoD": -100, "DoDP": -4.4, "Rev": 4559900}, {"date": "18/10/05", "OR": 2309, "HP": 2312, "LP": 2250, "CR": 2263, "DoD": -96, "DoDP": -4.1, "Rev": 4545300}, {"date": "18/10/04", "OR": 2419, "HP": 2427, "LP": 2341, "CR": 2359, "DoD": -46, "DoDP": -1.9, "Rev": 3640800}, {"date": "18/10/03", "OR": 2420, "HP": 2432, "LP": 2394, "CR": 2405, "DoD": -5, "DoDP": -0.2, "Rev": 2244700}, {"date": "18/10/02", "OR": 2432, "HP": 2445, "LP": 2398, "CR": 2410, "DoD": -43, "DoDP": -1.8, "Rev": 3563100}, {"date": "18/10/01", "OR": 2400, "HP": 2506, "LP": 2392, "CR": 2453, "DoD": 60, "DoDP": 2.5, "Rev": 4093600}, {"date": "18/09/28", "OR": 2422, "HP": 2445, "LP": 2373, "CR": 2393, "DoD": 14, "DoDP": 0.6, "Rev": 3354700}, {"date": "18/09/27", "OR": 2425, "HP": 2437, "LP": 2370, "CR": 2379, "DoD": -57, "DoDP": -2.3, "Rev": 2947100}, {"date": "18/09/26", "OR": 2429, "HP": 2475, "LP": 2388, "CR": 2436, "DoD": 6, "DoDP": 0.2, "Rev": 2415300}, {"date": "18/09/25", "OR": 2373, "HP": 2444, "LP": 2365, "CR": 2430, "DoD": 81, "DoDP": 3.4, "Rev": 3484100}, {"date": "18/09/21", "OR": 2392, "HP": 2395, "LP": 2344, "CR": 2349, "DoD": -15, "DoDP": -0.6, "Rev": 3890200}, {"date": "18/09/20", "OR": 2420, "HP": 2420, "LP": 2341, "CR": 2364, "DoD": -42, "DoDP": -1.7, "Rev": 3149800}, {"date": "18/09/19", "OR": 2442, "HP": 2460, "LP": 2401, "CR": 2406, "DoD": 38, "DoDP": 1.6, "Rev": 3837900}, {"date": "18/09/18", "OR": 2340, "HP": 2394, "LP": 2295, "CR": 2368, "DoD": 27, "DoDP": 1.2, "Rev": 3232600}, {"date": "18/09/14", "OR": 2297, "HP": 2346, "LP": 2261, "CR": 2341, "DoD": 111, "DoDP": 5, "Rev": 5256100}, {"date": "18/09/13", "OR": 2285, "HP": 2342, "LP": 2211, "CR": 2230, "DoD": -127, "DoDP": -5.4, "Rev": 5455700}, {"date": "18/09/12", "OR": 2417, "HP": 2429, "LP": 2334, "CR": 2357, "DoD": -90, "DoDP": -3.7, "Rev": 3414900}, {"date": "18/09/11", "OR": 2413, "HP": 2457, "LP": 2400, "CR": 2447, "DoD": 60, "DoDP": 2.5, "Rev": 2750200}, {"date": "18/09/10", "OR": 2435, "HP": 2441, "LP": 2370, "CR": 2387, "DoD": -59, "DoDP": -2.4, "Rev": 3909700}, {"date": "18/09/07", "OR": 2501, "HP": 2509, "LP": 2410, "CR": 2446, "DoD": -189, "DoDP": -7.2, "Rev": 5292900}, {"date": "18/09/06", "OR": 2688, "HP": 2695, "LP": 2615, "CR": 2635, "DoD": -75, "DoDP": -2.8, "Rev": 2101500}, {"date": "18/09/05", "OR": 2726, "HP": 2750, "LP": 2708, "CR": 2710, "DoD": 0, "DoDP": 0, "Rev": 1723800}, {"date": "18/09/04", "OR": 2684, "HP": 2723, "LP": 2684, "CR": 2710, "DoD": 38, "DoDP": 1.4, "Rev": 2622100}, {"date": "18/09/03", "OR": 2685, "HP": 2720, "LP": 2656, "CR": 2672, "DoD": 8, "DoDP": 0.3, "Rev": 2445900}, {"date": "18/08/31", "OR": 2625, "HP": 2667, "LP": 2599, "CR": 2664, "DoD": 13, "DoDP": 0.5, "Rev": 1679900}, {"date": "18/08/30", "OR": 2657, "HP": 2676, "LP": 2640, "CR": 2651, "DoD": 31, "DoDP": 1.2, "Rev": 2362900}, {"date": "18/08/29", "OR": 2594, "HP": 2636, "LP": 2583, "CR": 2620, "DoD": 50, "DoDP": 1.9, "Rev": 2305600}, {"date": "18/08/28", "OR": 2651, "HP": 2663, "LP": 2566, "CR": 2570, "DoD": -38, "DoDP": -1.5, "Rev": 2203500}, {"date": "18/08/27", "OR": 2574, "HP": 2613, "LP": 2562, "CR": 2608, "DoD": 48, "DoDP": 1.9, "Rev": 1567500}, {"date": "18/08/24", "OR": 2545, "HP": 2567, "LP": 2537, "CR": 2560, "DoD": 22, "DoDP": 0.9, "Rev": 1446000}, {"date": "18/08/23", "OR": 2533, "HP": 2546, "LP": 2516, "CR": 2538, "DoD": 24, "DoDP": 1, "Rev": 1504800}, {"date": "18/08/22", "OR": 2484, "HP": 2533, "LP": 2473, "CR": 2514, "DoD": 40, "DoDP": 1.6, "Rev": 1773600}, {"date": "18/08/21", "OR": 2421, "HP": 2475, "LP": 2407, "CR": 2474, "DoD": 49, "DoDP": 2, "Rev": 1735200}, {"date": "18/08/20", "OR": 2447, "HP": 2460, "LP": 2413, "CR": 2425, "DoD": -27, "DoDP": -1.1, "Rev": 1457300}, {"date": "18/08/17", "OR": 2500, "HP": 2504, "LP": 2427, "CR": 2452, "DoD": -5, "DoDP": -0.2, "Rev": 1950300}, {"date": "18/08/16", "OR": 2400, "HP": 2492, "LP": 2366, "CR": 2457, "DoD": 18, "DoDP": 0.7, "Rev": 2809200}, {"date": "18/08/15", "OR": 2429, "HP": 2444, "LP": 2412, "CR": 2439, "DoD": -21, "DoDP": -0.9, "Rev": 1628100}, {"date": "18/08/14", "OR": 2472, "HP": 2486, "LP": 2426, "CR": 2460, "DoD": 37, "DoDP": 1.5, "Rev": 3076500}, {"date": "18/08/13", "OR": 2485, "HP": 2490, "LP": 2395, "CR": 2423, "DoD": -107, "DoDP": -4.2, "Rev": 3872700}, {"date": "18/08/10", "OR": 2617, "HP": 2622, "LP": 2517, "CR": 2530, "DoD": -130, "DoDP": -4.9, "Rev": 4635000}, {"date": "18/08/09", "OR": 2680, "HP": 2688, "LP": 2653, "CR": 2660, "DoD": -29, "DoDP": -1.1, "Rev": 1753000}, {"date": "18/08/08", "OR": 2697, "HP": 2706, "LP": 2677, "CR": 2689, "DoD": 0, "DoDP": 0, "Rev": 1779600}, {"date": "18/08/07", "OR": 2700, "HP": 2711, "LP": 2668, "CR": 2689, "DoD": -9, "DoDP": -0.3, "Rev": 1328000}, {"date": "18/08/06", "OR": 2708, "HP": 2722, "LP": 2681, "CR": 2698, "DoD": -9, "DoDP": -0.3, "Rev": 1460100}, {"date": "18/08/03", "OR": 2709, "HP": 2743, "LP": 2692, "CR": 2707, "DoD": 24, "DoDP": 0.9, "Rev": 2561700}, {"date": "18/08/02", "OR": 2664, "HP": 2731, "LP": 2662, "CR": 2683, "DoD": 20, "DoDP": 0.8, "Rev": 2972300}, {"date": "18/08/01", "OR": 2659, "HP": 2678, "LP": 2648, "CR": 2663, "DoD": 19, "DoDP": 0.7, "Rev": 2150800}, {"date": "18/07/31", "OR": 2603, "HP": 2656, "LP": 2592, "CR": 2644, "DoD": 1, "DoDP": 0, "Rev": 2569200}, {"date": "18/07/30", "OR": 2650, "HP": 2692, "LP": 2635, "CR": 2643, "DoD": -30, "DoDP": -1.1, "Rev": 2790100}, {"date": "18/07/27", "OR": 2680, "HP": 2709, "LP": 2661, "CR": 2673, "DoD": 32, "DoDP": 1.2, "Rev": 3998900}, {"date": "18/07/26", "OR": 2700, "HP": 2710, "LP": 2578, "CR": 2641, "DoD": 156, "DoDP": 6.3, "Rev": 11100300}, {"date": "18/07/25", "OR": 2428, "HP": 2504, "LP": 2423, "CR": 2485, "DoD": 46, "DoDP": 1.9, "Rev": 3635100}, {"date": "18/07/24", "OR": 2420, "HP": 2467, "LP": 2405, "CR": 2439, "DoD": 46, "DoDP": 1.9, "Rev": 2410300}, {"date": "18/07/23", "OR": 2394, "HP": 2426, "LP": 2355, "CR": 2393, "DoD": -51, "DoDP": -2.1, "Rev": 2815400}, {"date": "18/07/20", "OR": 2461, "HP": 2529, "LP": 2421, "CR": 2444, "DoD": -80, "DoDP": -3.2, "Rev": 3588800}, {"date": "18/07/19", "OR": 2485, "HP": 2542, "LP": 2483, "CR": 2524, "DoD": 82, "DoDP": 3.4, "Rev": 3107700}, {"date": "18/07/18", "OR": 2450, "HP": 2482, "LP": 2426, "CR": 2442, "DoD": 36, "DoDP": 1.5, "Rev": 2234600}, {"date": "18/07/17", "OR": 2420, "HP": 2450, "LP": 2398, "CR": 2406, "DoD": -14, "DoDP": -0.6, "Rev": 2408900}, {"date": "18/07/13", "OR": 2398, "HP": 2434, "LP": 2386, "CR": 2420, "DoD": 64, "DoDP": 2.7, "Rev": 3129300}, {"date": "18/07/12", "OR": 2328, "HP": 2364, "LP": 2281, "CR": 2356, "DoD": 10, "DoDP": 0.4, "Rev": 2135000}, {"date": "18/07/11", "OR": 2325, "HP": 2370, "LP": 2287, "CR": 2346, "DoD": -18, "DoDP": -0.8, "Rev": 1927900}, {"date": "18/07/10", "OR": 2358, "HP": 2387, "LP": 2333, "CR": 2364, "DoD": 22, "DoDP": 0.9, "Rev": 1808200}, {"date": "18/07/09", "OR": 2353, "HP": 2378, "LP": 2339, "CR": 2342, "DoD": 57, "DoDP": 2.5, "Rev": 2844000}, {"date": "18/07/06", "OR": 2244, "HP": 2296, "LP": 2240, "CR": 2285, "DoD": 79, "DoDP": 3.6, "Rev": 2324200}, {"date": "18/07/05", "OR": 2178, "HP": 2242, "LP": 2174, "CR": 2206, "DoD": 17, "DoDP": 0.8, "Rev": 1908300}, {"date": "18/07/04", "OR": 2253, "HP": 2255, "LP": 2145, "CR": 2189, "DoD": -98, "DoDP": -4.3, "Rev": 3114900}, {"date": "18/07/03", "OR": 2261, "HP": 2291, "LP": 2244, "CR": 2287, "DoD": 17, "DoDP": 0.7, "Rev": 1660600}, {"date": "18/07/02", "OR": 2304, "HP": 2354, "LP": 2264, "CR": 2270, "DoD": -38, "DoDP": -1.6, "Rev": 2236900}, {"date": "18/06/29", "OR": 2350, "HP": 2352, "LP": 2280, "CR": 2308, "DoD": null, "DoDP": null, "Rev": 2817700}]